vrprot/__init__.py
vrprot/alphafold_db_parser.py
vrprot/argument_parser.py
vrprot/batcher.py
vrprot/classes.py
vrprot/exceptions.py
vrprot/overview_util.py
vrprot/pointcloud2map_8bit.py
vrprot/sample_pointcloud.py
vrprot/util.py
vrprot/scripts/chimerax_bundle.py
vrprot/scripts/combine_structures.py
vrprot/scripts/convertGLBtoPly.py
vrprot/scripts/easy_pipeline.py
vrprot/scripts/easy_pipeline_8bit.py
vrprot/scripts/extract_alphafold.sh
vrprot/scripts/get_scaling.py
vrprot/scripts/pointcloud2map.py
vrprot/scripts/pointcloud2map_8bit.py
vrprot/scripts/sample_pointcloud.py
vrprot/static/3d_objects/Cube_no_lines.ply
vrprot-0a4.dist-info/METADATA
vrprot-0a4.dist-info/WHEEL
vrprot-0a4.dist-info/licenses/LICENSE
vrprot-0a4.dist-info/RECORD
