Metadata-Version: 2.1
Name: vrprot
Version: 0a4
Summary: This package is used to generate your own protein structure images to represent 3D protein structures on the VRNetzer platform.
Project-URL: Homepage, https://menchelab.com/
Project-URL: Bug Tracker, https://github.com/menchelab/vrprot/issues
Project-URL: Git, https://github.com/menchelab/vrprot
Author: Felix F.
Author-email: "Till O." <till@menchelab.com>
Maintainer-email: "Till O." <till@menchelab.com>
License-File: LICENSE
Classifier: License :: OSI Approved :: MIT License
Classifier: Operating System :: OS Independent
Classifier: Programming Language :: Python :: 3
Requires-Python: >=3.9
Requires-Dist: asyncio>=3.4.3
Requires-Dist: open3d>=0.15.1
Requires-Dist: pandas>=1.5.0
Requires-Dist: pillow>=9.2.0
Requires-Dist: pyglet<2.0
Requires-Dist: requests>=2.28.1
Requires-Dist: tqdm
Requires-Dist: trimesh>=3.15.3
